libtest51/__init__.py
libtest51/__main__.py
libtest51/functions.py
libtest51/py.typed
libtest51-0.0.1.dist-info/LICENSE
libtest51-0.0.1.dist-info/METADATA
libtest51-0.0.1.dist-info/WHEEL
libtest51-0.0.1.dist-info/entry_points.txt
libtest51-0.0.1.dist-info/RECORD
