Metadata-Version: 2.1
Name: libtest51
Version: 0.0.1
Summary: Libtest51
Home-page: https://github.com/statisticsnorway/libtest51
License: MIT
Author: Magnus Kvåle Helliesen
Author-email: magnus.helliesen@gmail.com
Requires-Python: >=3.9,<4.0
Classifier: Development Status :: 4 - Beta
Classifier: License :: OSI Approved :: MIT License
Classifier: Programming Language :: Python :: 3
Classifier: Programming Language :: Python :: 3.9
Classifier: Programming Language :: Python :: 3.10
Classifier: Programming Language :: Python :: 3.11
Classifier: Programming Language :: Python :: 3.12
Requires-Dist: click (>=8.0.1)
Project-URL: Changelog, https://github.com/statisticsnorway/libtest51/releases
Project-URL: Documentation, https://statisticsnorway.github.io/libtest51
Project-URL: Repository, https://github.com/statisticsnorway/libtest51
